scratchhh/__init__.py
scratchhh/scratchhh.py
scratchhh-0.2.72.dist-info/LICENSE
scratchhh-0.2.72.dist-info/METADATA
scratchhh-0.2.72.dist-info/WHEEL
scratchhh-0.2.72.dist-info/top_level.txt
scratchhh-0.2.72.dist-info/RECORD
