Metadata-Version: 2.1
Name: scratchhh
Version: 0.2.72
Summary: Scratch API wrapper
Home-page: https://github.com/themysticsavages/scratchhh
Author: themysticsavages
License: MIT
Platform: UNKNOWN
Classifier: Programming Language :: Python :: 3
Classifier: License :: OSI Approved :: MIT License
Classifier: Operating System :: OS Independent
Requires-Python: >=3.6
License-File: LICENSE
Requires-Dist: requests
